README.md
pyproject.toml
trustgraph/base_version.py
trustgraph/exceptions.py
trustgraph/log_level.py
trustgraph/rdf.py
trustgraph/api/__init__.py
trustgraph/api/api.py
trustgraph/api/async_bulk_client.py
trustgraph/api/async_flow.py
trustgraph/api/async_metrics.py
trustgraph/api/async_socket_client.py
trustgraph/api/bulk_client.py
trustgraph/api/collection.py
trustgraph/api/config.py
trustgraph/api/exceptions.py
trustgraph/api/flow.py
trustgraph/api/knowledge.py
trustgraph/api/library.py
trustgraph/api/metrics.py
trustgraph/api/socket_client.py
trustgraph/api/types.py
trustgraph/base/__init__.py
trustgraph/base/agent_client.py
trustgraph/base/agent_service.py
trustgraph/base/async_processor.py
trustgraph/base/backend.py
trustgraph/base/cassandra_config.py
trustgraph/base/chunking_service.py
trustgraph/base/collection_config_handler.py
trustgraph/base/consumer.py
trustgraph/base/consumer_spec.py
trustgraph/base/document_embeddings_client.py
trustgraph/base/document_embeddings_query_service.py
trustgraph/base/document_embeddings_store_service.py
trustgraph/base/embeddings_client.py
trustgraph/base/embeddings_service.py
trustgraph/base/flow.py
trustgraph/base/flow_processor.py
trustgraph/base/graph_embeddings_client.py
trustgraph/base/graph_embeddings_query_service.py
trustgraph/base/graph_embeddings_store_service.py
trustgraph/base/graph_rag_client.py
trustgraph/base/llm_service.py
trustgraph/base/logging.py
trustgraph/base/metrics.py
trustgraph/base/parameter_spec.py
trustgraph/base/producer.py
trustgraph/base/producer_spec.py
trustgraph/base/prompt_client.py
trustgraph/base/publisher.py
trustgraph/base/pubsub.py
trustgraph/base/pulsar_backend.py
trustgraph/base/request_response_spec.py
trustgraph/base/spec.py
trustgraph/base/structured_query_client.py
trustgraph/base/subscriber.py
trustgraph/base/subscriber_spec.py
trustgraph/base/text_completion_client.py
trustgraph/base/tool_client.py
trustgraph/base/tool_service.py
trustgraph/base/triples_client.py
trustgraph_base.egg-info/PKG-INFO
trustgraph_base.egg-info/SOURCES.txt
trustgraph_base.egg-info/dependency_links.txt
trustgraph_base.egg-info/requires.txt
trustgraph_base.egg-info/top_level.txt